middleman/__init__.py
middleman/cli.py
middleman/client.py
middleman/models.py
middleman_ml-0.1.1.dist-info/METADATA
middleman_ml-0.1.1.dist-info/WHEEL
middleman_ml-0.1.1.dist-info/RECORD
