Metadata-Version: 2.4
Name: middleman-ml
Version: 0.1.1
Summary: Python SDK for Middleman GPU compute platform
Project-URL: Homepage, https://middleman.run
Project-URL: Documentation, https://docs.middleman.run
Project-URL: Repository, https://github.com/mkshepherd1/Middleman
Author-email: Middleman <support@middleman.run>
License-Expression: MIT
Keywords: cloud,compute,gpu,machine-learning,ml,training
Classifier: Development Status :: 4 - Beta
Classifier: Intended Audience :: Developers
Classifier: License :: OSI Approved :: MIT License
Classifier: Programming Language :: Python :: 3
Classifier: Programming Language :: Python :: 3.8
Classifier: Programming Language :: Python :: 3.9
Classifier: Programming Language :: Python :: 3.10
Classifier: Programming Language :: Python :: 3.11
Classifier: Programming Language :: Python :: 3.12
Classifier: Topic :: Scientific/Engineering :: Artificial Intelligence
Requires-Python: >=3.8
Requires-Dist: httpx>=0.24.0
Requires-Dist: pydantic>=2.0.0
